pqunique.py
pqunique-0.1.dist-info/DESCRIPTION.rst
pqunique-0.1.dist-info/METADATA
pqunique-0.1.dist-info/RECORD
pqunique-0.1.dist-info/WHEEL
pqunique-0.1.dist-info/metadata.json
pqunique-0.1.dist-info/top_level.txt
