Metadata-Version: 2.0
Name: pqunique
Version: 0.1
Summary: Priority queue with unique items
Home-page: https://github.com/Pastafarianist/pqunique
Author: Pastafarianist
Author-email: delonorm@gmail.com
License: MIT
Keywords: development queue priority
Platform: UNKNOWN
Classifier: Development Status :: 3 - Alpha
Classifier: Intended Audience :: Developers
Classifier: Topic :: Software Development :: Libraries :: Python Modules
Classifier: License :: OSI Approved :: MIT License
Classifier: Programming Language :: Python :: 3
Classifier: Programming Language :: Python :: 3.3
Classifier: Programming Language :: Python :: 3.4
Classifier: Programming Language :: Python :: 3.5
